fe/__init__.py
fe-0.1.dev0.dist-info/METADATA
fe-0.1.dev0.dist-info/WHEEL
fe-0.1.dev0.dist-info/top_level.txt
fe-0.1.dev0.dist-info/RECORD
